{
  "player": "teddy",
  "week": 15,
  "picks": {
    "Cleveland_Chicago_2025-12-14 13:00": {
      "spread": "Chicago",
      "total": "over"
    },
    "Arizona_Houston_2025-12-14 13:00": {
      "spread": "Arizona",
      "total": "under"
    },
    "LA Chargers_Kansas City_2025-12-14 13:00": {
      "spread": "LA Chargers",
      "total": "under"
    },
    "Baltimore_Cincinnati_2025-12-14 13:00": {
      "spread": "Cincinnati",
      "total": "over"
    },
    "NY Jets_Jacksonville_2025-12-14 13:00": {
      "spread": "Jacksonville",
      "total": "under"
    },
    "Buffalo_New England_2025-12-14 13:00": {
      "spread": "Buffalo",
      "total": "over"
    },
    "Washington_NY Giants_2025-12-14 13:00": {
      "spread": "NY Giants",
      "total": "under"
    },
    "Las Vegas_Philadelphia_2025-12-14 13:00": {
      "spread": "Las Vegas",
      "total": "under"
    },
    "Detroit_LA Rams_2025-12-14 16:25": {
      "spread": "Detroit",
      "total": "over"
    },
    "Indianapolis_Seattle_2025-12-14 16:25": {
      "spread": "Indianapolis",
      "total": "under"
    },
    "Tennessee_San Francisco_2025-12-14 16:25": {
      "spread": "Tennessee",
      "total": "under"
    },
    "Green Bay_Denver_2025-12-14 16:25": {
      "spread": "Green Bay",
      "total": "under"
    },
    "Carolina_New Orleans_2025-12-14 16:25": {
      "spread": "Carolina",
      "total": "over"
    },
    "Minnesota_Dallas_2025-12-14 20:20": {
      "spread": "Dallas",
      "total": "over"
    },
    "Miami_Pittsburgh_2025-12-15 20:15": {
      "spread": "Pittsburgh",
      "total": "over"
    }
  },
  "saved_at": "2025-12-14T17:33:30.334Z"
}