{
  "player": "will",
  "week": 6,
  "picks": {
    "Philadelphia_NY Giants_2025-10-09 20:15": {
      "spread": "NY Giants",
      "total": "over"
    },
    "Denver_NY Jets_2025-10-12 09:30": {
      "spread": "Denver",
      "total": "over"
    },
    "LA Rams_Baltimore_2025-10-12 13:00": {
      "spread": "LA Rams",
      "total": "over"
    },
    "Dallas_Carolina_2025-10-12 13:00": {
      "spread": "Dallas",
      "total": "under"
    },
    "Arizona_Indianapolis_2025-10-12 13:00": {
      "spread": "Indianapolis",
      "total": "under"
    },
    "Seattle_Jacksonville_2025-10-12 13:00": {
      "spread": "Jacksonville",
      "total": "over"
    },
    "LA Chargers_Miami_2025-10-12 13:00": {
      "spread": "LA Chargers",
      "total": "under"
    },
    "Cleveland_Pittsburgh_2025-10-12 13:00": {
      "spread": "Cleveland",
      "total": "over"
    },
    "New England_New Orleans_2025-10-12 13:00": {
      "spread": "New England",
      "total": "under"
    },
    "Tennessee_Las Vegas_2025-10-12 16:05": {
      "spread": "Las Vegas",
      "total": "over"
    },
    "San Francisco_Tampa Bay_2025-10-12 16:25": {
      "spread": "Tampa Bay",
      "total": "over"
    },
    "Cincinnati_Green Bay_2025-10-12 16:25": {
      "spread": "Green Bay",
      "total": "over"
    },
    "Detroit_Kansas City_2025-10-12 20:20": {
      "spread": "Detroit",
      "total": "over"
    },
    "Buffalo_Atlanta_2025-10-13 19:15": {
      "spread": "Buffalo",
      "total": "over"
    },
    "Chicago_Washington_2025-10-13 20:15": {
      "spread": "Chicago",
      "total": "over"
    }
  },
  "saved_at": "2025-10-12T17:05:18.755Z"
}